README
cobcreate.py
cobextract.py
setup.py
cobutils/__init__.py
cobutils/extract.py
cobutils/feo.py
cobutils/parser.py
cobutils/record.py
cobutils.egg-info/PKG-INFO
cobutils.egg-info/SOURCES.txt
cobutils.egg-info/dependency_links.txt
cobutils.egg-info/top_level.txt