Metadata-Version: 1.1
Name: cobutils
Version: 0.2.3
Summary: Manipulate cobol files from python
Home-page: https://pypi.python.org/pypi/cobutils
Author: Ferran Pegueroles Forcadell
Author-email: ferran@pegueroles.com
License: GPL
Platform: UNKNOWN
Classifier: Development Status :: 4 - Beta
Classifier: Intended Audience :: Information Technology
Classifier: License :: OSI Approved :: GNU Lesser General Public License v2 (LGPLv2)
Classifier: Programming Language :: Python :: 2
Classifier: Programming Language :: Python :: 2.6
Classifier: Programming Language :: Python :: 2.7
Classifier: Programming Language :: Python :: 3
Classifier: Programming Language :: Python :: 3.3
Classifier: Programming Language :: Python :: 3.4
Classifier: Programming Language :: Python :: 3.5
